{"is_source_file": false, "format": "", "description": "", "external_files": [], "external_methods": [], "published": [], "classes": [], "methods": [], "calls": [], "search-terms": [], "state": 2, "file_id": 8, "knowledge_revision": 103, "git_revision": "11e0f92dcad0c5be0fa81a91920ce22552f4553a", "hash": "eaf8d43e3fe744f033c5210146655d6c", "format-version": 4, "code-base-name": "frontend_react_app", "filename": "frontend_react_app/public/index.html", "revision_history": [{"103": "11e0f92dcad0c5be0fa81a91920ce22552f4553a"}]}